bareasgi/__init__.py
bareasgi/application.py
bareasgi/basic_router/__init__.py
bareasgi/basic_router/http_router.py
bareasgi/basic_router/path_definition.py
bareasgi/basic_router/path_segment.py
bareasgi/basic_router/web_socket_router.py
bareasgi/core_application.py
bareasgi/http/__init__.py
bareasgi/http/http_callbacks.py
bareasgi/http/http_errors.py
bareasgi/http/http_instance.py
bareasgi/http/http_middleware.py
bareasgi/http/http_request.py
bareasgi/http/http_response.py
bareasgi/http/http_router.py
bareasgi/lifespan/__init__.py
bareasgi/lifespan/lifespan_instance.py
bareasgi/lifespan/lifespan_request.py
bareasgi/middlewares/__init__.py
bareasgi/middlewares/compression.py
bareasgi/py.typed
bareasgi/utils.py
bareasgi/websockets/__init__.py
bareasgi/websockets/websocket.py
bareasgi/websockets/websocket_callbacks.py
bareasgi/websockets/websocket_errors.py
bareasgi/websockets/websocket_instance.py
bareasgi/websockets/websocket_middleware.py
bareasgi/websockets/websocket_request.py
bareasgi/websockets/websocket_router.py
bareasgi-4.4.1.dist-info/LICENSE
bareasgi-4.4.1.dist-info/WHEEL
bareasgi-4.4.1.dist-info/METADATA
bareasgi-4.4.1.dist-info/RECORD
