Metadata-Version: 2.1
Name: bareasgi
Version: 4.4.1
Summary: A lightweight ASGI framework
Home-page: https://github.com/rob-blackbourn/bareasgi
License: Apache-2.0
Author: Rob Blackbourn
Author-email: rob.blackbourn@gmail.com
Requires-Python: >=3.8,<4.0
Classifier: License :: OSI Approved :: Apache Software License
Classifier: Programming Language :: Python :: 3
Classifier: Programming Language :: Python :: 3.8
Classifier: Programming Language :: Python :: 3.9
Classifier: Programming Language :: Python :: 3.10
Classifier: Programming Language :: Python :: 3.11
Requires-Dist: bareutils (>=4.0.0,<5.0.0)
Requires-Dist: jetblack-asgi-typing (>=0.4.0,<0.5.0)
Project-URL: Documentation, https://rob-blackbourn.github.io/bareASGI
Project-URL: Repository, https://github.com/rob-blackbourn/bareasgi
